sphinx_material_saltstack/__init__.py
sphinx_material_saltstack/version.py
sphinx_material_saltstack/sphinx_material_saltstack/comments.html
sphinx_material_saltstack/sphinx_material_saltstack/globaltoc.html
sphinx_material_saltstack/sphinx_material_saltstack/google_analytics.html
sphinx_material_saltstack/sphinx_material_saltstack/header.html
sphinx_material_saltstack/sphinx_material_saltstack/hero.html
sphinx_material_saltstack/sphinx_material_saltstack/layout.html
sphinx_material_saltstack/sphinx_material_saltstack/localtoc.html
sphinx_material_saltstack/sphinx_material_saltstack/logo-text.html
sphinx_material_saltstack/sphinx_material_saltstack/page.html
sphinx_material_saltstack/sphinx_material_saltstack/relbar.html
sphinx_material_saltstack/sphinx_material_saltstack/repo.html
sphinx_material_saltstack/sphinx_material_saltstack/search.html
sphinx_material_saltstack/sphinx_material_saltstack/searchbox.html
sphinx_material_saltstack/sphinx_material_saltstack/sidebar.html
sphinx_material_saltstack/sphinx_material_saltstack/sourcelink.html
sphinx_material_saltstack/sphinx_material_saltstack/theme.conf
sphinx_material_saltstack/sphinx_material_saltstack/version_dropdown.html
sphinx_material_saltstack/sphinx_material_saltstack/static/jquery.js
sphinx_material_saltstack/sphinx_material_saltstack/static/jquery.min.map
sphinx_material_saltstack/sphinx_material_saltstack/static/material.css_t
sphinx_material_saltstack/sphinx_material_saltstack/static/fonts/font-awesome.css
sphinx_material_saltstack/sphinx_material_saltstack/static/fonts/material-icons.css
sphinx_material_saltstack/sphinx_material_saltstack/static/fonts/specimen/FontAwesome.ttf
sphinx_material_saltstack/sphinx_material_saltstack/static/fonts/specimen/FontAwesome.woff
sphinx_material_saltstack/sphinx_material_saltstack/static/fonts/specimen/FontAwesome.woff2
sphinx_material_saltstack/sphinx_material_saltstack/static/fonts/specimen/MaterialIcons-Regular.ttf
sphinx_material_saltstack-1.0.5.dist-info/LICENSE.md
sphinx_material_saltstack-1.0.5.dist-info/METADATA
sphinx_material_saltstack-1.0.5.dist-info/WHEEL
sphinx_material_saltstack-1.0.5.dist-info/entry_points.txt
sphinx_material_saltstack-1.0.5.dist-info/top_level.txt
sphinx_material_saltstack-1.0.5.dist-info/RECORD
