Metadata-Version: 2.1
Name: sphinx-material-saltstack
Version: 1.0.5
Summary: Material sphinx theme for SaltStack documentation
Home-page: https://gitlab.com/saltstack/open/docs/sphinx-material-saltstack
Author: Derek Ardolf
Author-email: derek@icanteven.io
License: UNKNOWN
Platform: UNKNOWN
Classifier: Intended Audience :: Developers
Classifier: Natural Language :: English
Classifier: License :: OSI Approved :: Apache Software License
Classifier: Framework :: Sphinx :: Extension
Classifier: Framework :: Sphinx :: Theme
Classifier: Topic :: Documentation :: Sphinx
Classifier: Programming Language :: Python
Classifier: Programming Language :: Python :: 3
Classifier: Programming Language :: Python :: 3 :: Only
Classifier: Programming Language :: Python :: 3.6
Classifier: Programming Language :: Python :: 3.7
Classifier: Programming Language :: Python :: 3.8
Classifier: Development Status :: 5 - Production/Stable
Requires-Python: >=3.6
Requires-Dist: sphinx (>=3.0)
Requires-Dist: beautifulsoup4 (==4.9.1)
Requires-Dist: python-slugify[unidecode] (==4.0.1)
Requires-Dist: css-html-js-minify (==2.5.5)
Requires-Dist: lxml (==4.5.2)
